README.rst
setup.py
bin/pygists
pygists/__init__.py
pygists/__main__.py
pygists/cli.py
pygists/handlers.py
pygists/pygists.py
pygists.egg-info/PKG-INFO
pygists.egg-info/SOURCES.txt
pygists.egg-info/dependency_links.txt
pygists.egg-info/requires.txt
pygists.egg-info/top_level.txt
pygists/models/__init__.py
pygists/models/gist.py