Metadata-Version: 1.1
Name: pygists
Version: 1.1.0
Summary: CLI tool to operate with the GitHub Gists API.
Home-page: https://github.com/tomasfarias/Pygists
Author: Tomas Farias
Author-email: tomasfariassantana@gmail.com
License: MIT
Platform: UNKNOWN
Classifier: Development Status :: 5 - Production/Stable
Classifier: License :: OSI Approved :: MIT License
Classifier: Programming Language :: Python
Classifier: Programming Language :: Python :: 3.7
Classifier: Programming Language :: Python :: 3.8
Classifier: Operating System :: OS Independent
